Metadata-Version: 2.1
Name: nsvb
Version: 0.2.1
Summary: National Scale Volume and Biomass Estimators
Home-page: https://github.com/silvxlabs/nsvb
License: MIT
Project-URL: Bug Tracker, https://github.com/silvxlabs/nsvb/issues
Classifier: Intended Audience :: Developers
Classifier: Intended Audience :: Science/Research
Classifier: License :: OSI Approved :: MIT License
Classifier: Operating System :: OS Independent
Classifier: Programming Language :: Python :: 3
Classifier: Programming Language :: Python :: 3.9
Classifier: Programming Language :: Python :: 3.10
Classifier: Programming Language :: Python :: 3.11
Classifier: Programming Language :: Python :: 3.12
Classifier: Topic :: Scientific/Engineering
Requires-Python: >=3.9
License-File: LICENSE
